isotp/__init__.py
isotp/address.py
isotp/can_message.py
isotp/errors.py
isotp/protocol.py
isotp/py.typed
isotp/tools.py
isotp/tpsock/__init__.py
isotp/tpsock/opts.py
can_isotp-2.0.6.dist-info/LICENSE.txt
can_isotp-2.0.6.dist-info/METADATA
can_isotp-2.0.6.dist-info/WHEEL
can_isotp-2.0.6.dist-info/top_level.txt
can_isotp-2.0.6.dist-info/RECORD
