Metadata-Version: 2.1
Name: can-isotp
Version: 2.0.6
Summary: Module enabling the IsoTP protocol defined by ISO-15765
Home-page: https://github.com/pylessard/python-can-isotp
Download-URL: https://github.com/pylessard/python-can-isotp/archive/v2.0.6.tar.gz
Author: Pier-Yves Lessard
Author-email: py.lessard@gmail.com
License: MIT
Keywords: isotp,can,iso-15765,15765,iso15765
Classifier: Programming Language :: Python
Classifier: Programming Language :: Python :: 3
Classifier: Development Status :: 4 - Beta
Classifier: Operating System :: POSIX :: Linux
Classifier: Intended Audience :: Developers
Classifier: License :: OSI Approved :: MIT License
Classifier: Topic :: Scientific/Engineering :: Interface Engine/Protocol Translator
Requires-Python: >=3.7
License-File: LICENSE.txt
Provides-Extra: dev
Requires-Dist: mypy ; extra == 'dev'
Requires-Dist: ipdb ; extra == 'dev'
Requires-Dist: autopep8 ; extra == 'dev'
Requires-Dist: coverage ; extra == 'dev'
Requires-Dist: python-can ; extra == 'dev'
Provides-Extra: test
Requires-Dist: mypy ; extra == 'test'
Requires-Dist: coverage ; extra == 'test'
Requires-Dist: python-can ; extra == 'test'
